team_digest/__init__.py
team_digest/__main__.py
team_digest/_footer.py
team_digest/slack_delivery.py
team_digest/team_digest_runtime.py
team_digest/team_digest_version.py
team_digest/team_email_digest.py
team_digest/examples/README.md
team_digest/examples/configs/daily.yml
team_digest/examples/configs/monthly.yml
team_digest/examples/configs/weekly.yml
team_digest/examples/logs/notes-2025-10-13.md
team_digest/examples/logs/notes-2025-10-14.md
team_digest/examples/logs/notes-2025-10-15.md
team_digest/examples/logs/notes-2025-10-16.md
team_digest/examples/logs/notes-2025-10-17.md
team_digest/examples/logs/sample.md
team_digest-1.1.18.data/data/share/team-digest/LICENSE
team_digest-1.1.18.data/data/share/team-digest/README.md
team_digest-1.1.18.data/data/share/team-digest/USAGE.md
team_digest-1.1.18.dist-info/licenses/LICENSE
team_digest-1.1.18.dist-info/METADATA
team_digest-1.1.18.dist-info/WHEEL
team_digest-1.1.18.dist-info/entry_points.txt
team_digest-1.1.18.dist-info/top_level.txt
team_digest-1.1.18.dist-info/RECORD
