Metadata-Version: 2.4
Name: team-digest
Version: 1.1.18
Summary: Generate daily/weekly/monthly team digests from Markdown logs; optional Slack posting.
Author: Anuraj Deol
License: 
Project-URL: Homepage, https://github.com/AnurajDeol1990/team-digest
Project-URL: Repository, https://github.com/AnurajDeol1990/team-digest
Project-URL: Issues, https://github.com/AnurajDeol1990/team-digest/issues
Keywords: digest,email,slack,automation,markdown,teams
Classifier: Programming Language :: Python :: 3
Classifier: Programming Language :: Python :: 3 :: Only
Classifier: Programming Language :: Python :: 3.9
Classifier: Programming Language :: Python :: 3.10
Classifier: Programming Language :: Python :: 3.11
Classifier: Programming Language :: Python :: 3.12
Classifier: Programming Language :: Python :: 3.13
Classifier: License :: OSI Approved :: MIT License
Classifier: Operating System :: OS Independent
Classifier: Intended Audience :: Information Technology
Classifier: Topic :: Office/Business
Classifier: Topic :: Utilities
Requires-Python: >=3.9
License-File: LICENSE
Requires-Dist: PyYAML<7,>=6
Requires-Dist: python-dateutil<3,>=2.8
Requires-Dist: regex>=2023.0.0
Requires-Dist: requests<3,>=2.31
Requires-Dist: tqdm<5,>=4
Dynamic: license-file
